brent/__init__.py
brent/common.py
brent/datasets.py
brent/examples.py
brent/graph.py
brent/query.py
brent/sklearn.py
brent/parsers/__init__.py
brent/parsers/bif.py
brent-0.2.4.dist-info/LICENSE
brent-0.2.4.dist-info/METADATA
brent-0.2.4.dist-info/WHEEL
brent-0.2.4.dist-info/top_level.txt
brent-0.2.4.dist-info/RECORD
