Metadata-Version: 2.1
Name: brent
Version: 0.2.4
Summary: UNKNOWN
Home-page: UNKNOWN
License: UNKNOWN
Keywords: causal,bayesian,graphical,model,inference
Platform: UNKNOWN
Classifier: Intended Audience :: Developers
Classifier: Intended Audience :: Science/Research
Classifier: Programming Language :: Python :: 3.6
Classifier: Programming Language :: Python :: 3.7
Classifier: Development Status :: 3 - Alpha
Classifier: License :: OSI Approved :: MIT License
Classifier: Topic :: Scientific/Engineering
Classifier: Topic :: Scientific/Engineering :: Artificial Intelligence
Requires-Python: >=3.6
Requires-Dist: numpy (>=1.15.4)
Requires-Dist: scipy (>=1.2.0)
Requires-Dist: scikit-learn (>=0.20.2)
Requires-Dist: pandas (>=0.23.4)
Requires-Dist: matplotlib (>=3.0.2)
Requires-Dist: networkx (>=2.2)
Requires-Dist: graphviz (>=0.10.1)
Provides-Extra: dev
Requires-Dist: flake8 (>=3.6.0) ; extra == 'dev'
Requires-Dist: pytest (>=3.3.1) ; extra == 'dev'
Requires-Dist: pdoc3 (>=0.5.2) ; extra == 'dev'
Requires-Dist: nbval (>=0.9.1) ; extra == 'dev'
Requires-Dist: plotnine (>=0.5.1) ; extra == 'dev'
Requires-Dist: twine (>=1.13.0) ; extra == 'dev'
